{
  "swagger": "2.0",
  "info": {
    "title": "Category Attribute - bg.goods.parentspec.get",
    "description": "用于发布时查询父规格列表",
    "version": "2025-03-13 15:57:46"
  },
  "consumes": [
    "application/json"
  ],
  "produces": [
    "application/json"
  ],
  "basePath": "/",
  "paths": {
    "/openapi/router": {
      "post": {
        "tags": [
          "Category Attribute"
        ],
        "operationId": "bg_goods_parentspec_get",
        "summary": "查询父规格列表",
        "description": "用于发布时查询父规格列表",
        "parameters": [
          {
            "name": "body",
            "in": "body",
            "required": true,
            "description": "Temu router request body. The `type` field must be `bg.goods.parentspec.get`.",
            "schema": {
              "$ref": "#/definitions/bg_goods_parentspec_getRequest"
            }
          }
        ],
        "responses": {
          "200": {
            "description": "Temu API response.",
            "schema": {
              "$ref": "#/definitions/bg_goods_parentspec_getResponse"
            }
          }
        },
        "x-temu-api-type": "bg.goods.parentspec.get",
        "x-temu-region-module": "temu-cn-api",
        "x-temu-group": {
          "title": "Category Attribute",
          "sourceTitle": "类目属性API组",
          "directory": "category-attribute-api"
        },
        "x-temu-gateway": {
          "method": "POST",
          "url": "/openapi/router",
          "routerTypeParameter": "type",
          "note": "CN source tables state /openapi/router. Use the CN host configured for the seller application."
        },
        "x-temu-endpoint-table": [
          {
            "调用地址/地区": "/openapi/router",
            "数据存储": "CN"
          }
        ],
        "x-temu-last-update-time": "2025-03-13 15:57:46",
        "x-temu-common-parameters": [
          {
            "name": "type",
            "type": "STRING",
            "required": true,
            "description": "API接口名, 形如:bg.*"
          },
          {
            "name": "app_key",
            "type": "STRING",
            "required": true,
            "description": "已创建成功的应用标志"
          },
          {
            "name": "timestamp",
            "type": "STRING",
            "required": true,
            "description": "时间戳，格式为UNIX时间（秒） ，长度10位，当前时间-300秒<=入参时间<=当前时间+300秒"
          },
          {
            "name": "sign",
            "type": "STRING",
            "required": true,
            "description": "API入参参数签名，签名值根据如下算法给出计算过程"
          },
          {
            "name": "data_type",
            "type": "STRING",
            "required": false,
            "description": "请求返回的数据格式，可选参数固定为JSON"
          },
          {
            "name": "access_token",
            "type": "STRING",
            "required": true,
            "description": "用户授权令牌access_token，卖家中心—授权管理，申请授权生成"
          },
          {
            "name": "version",
            "type": "STRING",
            "required": true,
            "description": "API版本，默认为V1，无要求不传此参数"
          }
        ],
        "x-temu-request-parameters": [],
        "x-temu-response-parameters": [
          {
            "name": "result",
            "type": "OBJECT",
            "description": "result"
          },
          {
            "name": "parentSpecDTOS",
            "type": "LIST",
            "description": "父规格列表"
          },
          {
            "name": "$item",
            "type": "OBJECT",
            "description": "-"
          },
          {
            "name": "parentSpecName",
            "type": "STRING",
            "description": "父规格名称"
          },
          {
            "name": "parentSpecId",
            "type": "INTEGER",
            "description": "父规格id"
          },
          {
            "name": "success",
            "type": "BOOLEAN",
            "description": "status"
          },
          {
            "name": "errorCode",
            "type": "INTEGER",
            "description": "error code"
          },
          {
            "name": "errorMsg",
            "type": "STRING",
            "description": "error message"
          }
        ],
        "x-temu-additional-tables": [
          {
            "label": "返回错误码说明",
            "rows": [
              {
                "错误码": "1000001",
                "错误描述": "服务器开小差",
                "解决办法": "一般为系统抖动，可尝试重试，如果还是不行请联系管理员"
              }
            ]
          }
        ],
        "x-temu-source": {
          "document": "Temu CN API文档.md",
          "path": "C:\\Users\\Administrator\\Downloads\\Temu CN API文档.md",
          "startLine": 4776,
          "endLine": 4840,
          "contentSha256": "2c817bbf0c7a55196deb7fffadcc396a5b0fedb23a569d302b72f5b28327275d"
        }
      }
    }
  },
  "definitions": {
    "bg_goods_parentspec_getRequest": {
      "type": "object",
      "additionalProperties": true,
      "properties": {
        "type": {
          "type": "string",
          "x-temu-type": "STRING",
          "description": "API接口名, 形如:bg.* Must be `bg.goods.parentspec.get` for this operation.",
          "enum": [
            "bg.goods.parentspec.get"
          ],
          "default": "bg.goods.parentspec.get"
        },
        "app_key": {
          "type": "string",
          "x-temu-type": "STRING",
          "description": "已创建成功的应用标志"
        },
        "timestamp": {
          "type": "string",
          "x-temu-type": "STRING",
          "description": "时间戳，格式为UNIX时间（秒） ，长度10位，当前时间-300秒<=入参时间<=当前时间+300秒"
        },
        "sign": {
          "type": "string",
          "x-temu-type": "STRING",
          "description": "API入参参数签名，签名值根据如下算法给出计算过程"
        },
        "data_type": {
          "type": "string",
          "x-temu-type": "STRING",
          "description": "请求返回的数据格式，可选参数固定为JSON"
        },
        "access_token": {
          "type": "string",
          "x-temu-type": "STRING",
          "description": "用户授权令牌access_token，卖家中心—授权管理，申请授权生成"
        },
        "version": {
          "type": "string",
          "x-temu-type": "STRING",
          "description": "API版本，默认为V1，无要求不传此参数"
        }
      },
      "required": [
        "type",
        "app_key",
        "timestamp",
        "sign",
        "access_token",
        "version"
      ]
    },
    "bg_goods_parentspec_getResponse": {
      "type": "object",
      "additionalProperties": true,
      "properties": {
        "result": {
          "type": "object",
          "additionalProperties": true,
          "x-temu-type": "OBJECT",
          "description": "result"
        },
        "parentSpecDTOS": {
          "type": "array",
          "items": {
            "type": "object"
          },
          "x-temu-type": "LIST",
          "description": "父规格列表"
        },
        "parentSpecName": {
          "type": "string",
          "x-temu-type": "STRING",
          "description": "父规格名称"
        },
        "parentSpecId": {
          "type": "integer",
          "format": "int32",
          "x-temu-type": "INTEGER",
          "description": "父规格id"
        },
        "success": {
          "type": "boolean",
          "x-temu-type": "BOOLEAN",
          "description": "status"
        },
        "errorCode": {
          "type": "integer",
          "format": "int32",
          "x-temu-type": "INTEGER",
          "description": "error code"
        },
        "errorMsg": {
          "type": "string",
          "x-temu-type": "STRING",
          "description": "error message"
        }
      }
    }
  },
  "x-temu-source": {
    "document": "Temu CN API文档.md",
    "path": "C:\\Users\\Administrator\\Downloads\\Temu CN API文档.md",
    "startLine": 4776,
    "endLine": 4840,
    "contentSha256": "2c817bbf0c7a55196deb7fffadcc396a5b0fedb23a569d302b72f5b28327275d"
  },
  "x-temu-api-type": "bg.goods.parentspec.get",
  "x-temu-region-module": "temu-cn-api"
}
