{
  "swagger": "2.0",
  "info": {
    "title": "Instruction File - bg.goods.translationresult.get",
    "description": "查询说明书翻译结果",
    "version": "2025-03-26 17:35:32"
  },
  "consumes": [
    "application/json"
  ],
  "produces": [
    "application/json"
  ],
  "basePath": "/",
  "paths": {
    "/openapi/router": {
      "post": {
        "tags": [
          "Instruction File"
        ],
        "operationId": "bg_goods_translationresult_get",
        "summary": "查询说明书翻译结果",
        "description": "查询说明书翻译结果",
        "parameters": [
          {
            "name": "body",
            "in": "body",
            "required": true,
            "description": "Temu router request body. The `type` field must be `bg.goods.translationresult.get`.",
            "schema": {
              "$ref": "#/definitions/bg_goods_translationresult_getRequest"
            }
          }
        ],
        "responses": {
          "200": {
            "description": "Temu API response.",
            "schema": {
              "$ref": "#/definitions/bg_goods_translationresult_getResponse"
            }
          }
        },
        "x-temu-api-type": "bg.goods.translationresult.get",
        "x-temu-region-module": "temu-cn-api",
        "x-temu-group": {
          "title": "Instruction File",
          "sourceTitle": "说明书API组",
          "directory": "instruction-file-api"
        },
        "x-temu-gateway": {
          "method": "POST",
          "url": "/openapi/router",
          "routerTypeParameter": "type",
          "note": "CN source tables state /openapi/router. Use the CN host configured for the seller application."
        },
        "x-temu-endpoint-table": [
          {
            "调用地址/地区": "/openapi/router",
            "数据存储": "CN"
          }
        ],
        "x-temu-last-update-time": "2025-03-26 17:35:32",
        "x-temu-common-parameters": [
          {
            "name": "type",
            "type": "STRING",
            "required": true,
            "description": "API接口名, 形如:bg.*"
          },
          {
            "name": "app_key",
            "type": "STRING",
            "required": true,
            "description": "已创建成功的应用标志"
          },
          {
            "name": "timestamp",
            "type": "STRING",
            "required": true,
            "description": "时间戳，格式为UNIX时间（秒） ，长度10位，当前时间-300秒<=入参时间<=当前时间+300秒"
          },
          {
            "name": "sign",
            "type": "STRING",
            "required": true,
            "description": "API入参参数签名，签名值根据如下算法给出计算过程"
          },
          {
            "name": "data_type",
            "type": "STRING",
            "required": false,
            "description": "请求返回的数据格式，可选参数固定为JSON"
          },
          {
            "name": "access_token",
            "type": "STRING",
            "required": true,
            "description": "用户授权令牌access_token，卖家中心—授权管理，申请授权生成"
          },
          {
            "name": "version",
            "type": "STRING",
            "required": true,
            "description": "API版本，默认为V1，无要求不传此参数"
          }
        ],
        "x-temu-request-parameters": [
          {
            "name": "translateId",
            "type": "INTEGER",
            "required": true,
            "description": "翻译记录ID"
          },
          {
            "name": "supplierId",
            "type": "INTEGER",
            "required": true,
            "description": "供应商ID"
          }
        ],
        "x-temu-response-parameters": [
          {
            "name": "result",
            "type": "OBJECT",
            "description": "result"
          },
          {
            "name": "pdfId",
            "type": "INTEGER",
            "description": "PDF文件ID"
          },
          {
            "name": "languages",
            "type": "LIST",
            "description": "语种"
          },
          {
            "name": "$item",
            "type": "STRING",
            "description": "-"
          },
          {
            "name": "finished",
            "type": "BOOLEAN",
            "description": "是否完成"
          },
          {
            "name": "failReason",
            "type": "STRING",
            "description": "失败原因"
          },
          {
            "name": "success",
            "type": "BOOLEAN",
            "description": "status"
          },
          {
            "name": "errorCode",
            "type": "INTEGER",
            "description": "error code"
          },
          {
            "name": "errorMsg",
            "type": "STRING",
            "description": "error message"
          }
        ],
        "x-temu-additional-tables": [
          {
            "label": "返回错误码说明",
            "rows": [
              {
                "错误码": "2000000",
                "错误描述": "BUSINESS_EXCEPTION",
                "解决办法": "结合具体报错文案排查，如有疑问请联系管理员"
              },
              {
                "错误码": "3000000",
                "错误描述": "BAD_PARAMS",
                "解决办法": "参数错误，结合具体报错文案排查，如有疑问请联系管理员"
              }
            ]
          }
        ],
        "x-temu-source": {
          "document": "Temu CN API文档.md",
          "path": "C:\\Users\\Administrator\\Downloads\\Temu CN API文档.md",
          "startLine": 4363,
          "endLine": 4428,
          "contentSha256": "52531e7e3e8608b04a22b053eeef2fe01a0721da798d5d2abdd44717765f26dd"
        }
      }
    }
  },
  "definitions": {
    "bg_goods_translationresult_getRequest": {
      "type": "object",
      "additionalProperties": true,
      "properties": {
        "type": {
          "type": "string",
          "x-temu-type": "STRING",
          "description": "API接口名, 形如:bg.* Must be `bg.goods.translationresult.get` for this operation.",
          "enum": [
            "bg.goods.translationresult.get"
          ],
          "default": "bg.goods.translationresult.get"
        },
        "app_key": {
          "type": "string",
          "x-temu-type": "STRING",
          "description": "已创建成功的应用标志"
        },
        "timestamp": {
          "type": "string",
          "x-temu-type": "STRING",
          "description": "时间戳，格式为UNIX时间（秒） ，长度10位，当前时间-300秒<=入参时间<=当前时间+300秒"
        },
        "sign": {
          "type": "string",
          "x-temu-type": "STRING",
          "description": "API入参参数签名，签名值根据如下算法给出计算过程"
        },
        "data_type": {
          "type": "string",
          "x-temu-type": "STRING",
          "description": "请求返回的数据格式，可选参数固定为JSON"
        },
        "access_token": {
          "type": "string",
          "x-temu-type": "STRING",
          "description": "用户授权令牌access_token，卖家中心—授权管理，申请授权生成"
        },
        "version": {
          "type": "string",
          "x-temu-type": "STRING",
          "description": "API版本，默认为V1，无要求不传此参数"
        },
        "translateId": {
          "type": "integer",
          "format": "int32",
          "x-temu-type": "INTEGER",
          "description": "翻译记录ID"
        },
        "supplierId": {
          "type": "integer",
          "format": "int32",
          "x-temu-type": "INTEGER",
          "description": "供应商ID"
        }
      },
      "required": [
        "type",
        "app_key",
        "timestamp",
        "sign",
        "access_token",
        "version",
        "translateId",
        "supplierId"
      ]
    },
    "bg_goods_translationresult_getResponse": {
      "type": "object",
      "additionalProperties": true,
      "properties": {
        "result": {
          "type": "object",
          "additionalProperties": true,
          "x-temu-type": "OBJECT",
          "description": "result"
        },
        "pdfId": {
          "type": "integer",
          "format": "int32",
          "x-temu-type": "INTEGER",
          "description": "PDF文件ID"
        },
        "languages": {
          "type": "array",
          "items": {
            "type": "object"
          },
          "x-temu-type": "LIST",
          "description": "语种"
        },
        "finished": {
          "type": "boolean",
          "x-temu-type": "BOOLEAN",
          "description": "是否完成"
        },
        "failReason": {
          "type": "string",
          "x-temu-type": "STRING",
          "description": "失败原因"
        },
        "success": {
          "type": "boolean",
          "x-temu-type": "BOOLEAN",
          "description": "status"
        },
        "errorCode": {
          "type": "integer",
          "format": "int32",
          "x-temu-type": "INTEGER",
          "description": "error code"
        },
        "errorMsg": {
          "type": "string",
          "x-temu-type": "STRING",
          "description": "error message"
        }
      }
    }
  },
  "x-temu-source": {
    "document": "Temu CN API文档.md",
    "path": "C:\\Users\\Administrator\\Downloads\\Temu CN API文档.md",
    "startLine": 4363,
    "endLine": 4428,
    "contentSha256": "52531e7e3e8608b04a22b053eeef2fe01a0721da798d5d2abdd44717765f26dd"
  },
  "x-temu-api-type": "bg.goods.translationresult.get",
  "x-temu-region-module": "temu-cn-api"
}
