{
  "swagger": "2.0",
  "info": {
    "title": "Return And Refund - temu.aftersales.refund.issue",
    "description": "This interface is designed to enable merchants to efficiently process refund requests within the e-commerce platform.",
    "version": "2025-06-15 22:43:56"
  },
  "host": "openapi-b-global.temu.com",
  "schemes": [
    "https"
  ],
  "consumes": [
    "application/json"
  ],
  "produces": [
    "application/json"
  ],
  "basePath": "/",
  "paths": {
    "/openapi/router": {
      "post": {
        "tags": [
          "Return And Refund"
        ],
        "operationId": "temu_aftersales_refund_issue",
        "summary": "This interface is designed to enable merchants to efficiently process refund requests within the e-commerce platform.",
        "description": "This interface is designed to enable merchants to efficiently process refund requests within the e-commerce platform.",
        "parameters": [
          {
            "name": "body",
            "in": "body",
            "required": true,
            "description": "Temu router request body. The `type` field must be `temu.aftersales.refund.issue`.",
            "schema": {
              "$ref": "#/definitions/temu_aftersales_refund_issueRequest"
            }
          }
        ],
        "responses": {
          "200": {
            "description": "Temu API response.",
            "schema": {
              "$ref": "#/definitions/temu_aftersales_refund_issueResponse"
            }
          }
        },
        "x-temu-api-type": "temu.aftersales.refund.issue",
        "x-temu-region-module": "temu-global-api",
        "x-temu-group": {
          "title": "Return And Refund",
          "sourceTitle": "7、Return and Refund",
          "directory": "return-refund-api"
        },
        "x-temu-gateway": {
          "method": "POST",
          "url": "https://openapi-b-global.temu.com/openapi/router",
          "routerTypeParameter": "type"
        },
        "x-temu-endpoint-table": [
          {
            "Request URL": "POSThttps://openapi-b-global.temu.com/openapi/router",
            "Site Region": "GLOBAL"
          }
        ],
        "x-temu-audience": [
          "Cross Border",
          "Local"
        ],
        "x-temu-last-update-time": "2025-06-15 22:43:56",
        "x-temu-common-parameters": [
          {
            "name": "type",
            "type": "STRING",
            "required": true,
            "description": "API name,eg:bg.*"
          },
          {
            "name": "app_key",
            "type": "STRING",
            "required": true
          },
          {
            "name": "access_token",
            "type": "STRING",
            "required": true,
            "description": "A secure token for access control."
          },
          {
            "name": "sign",
            "type": "STRING",
            "required": true
          },
          {
            "name": "timestamp",
            "type": "STRING",
            "required": true,
            "description": "The timestamp is in UNIX time format (seconds), with a length of 10 digits, and should be within a range of 300 seconds before the current time to 300 seconds after the current time."
          },
          {
            "name": "data_type",
            "type": "STRING",
            "required": false,
            "description": "The data format of the request response is fixed as JSON for optional parameters."
          },
          {
            "name": "version",
            "type": "STRING",
            "required": false,
            "description": "API version, defaults to V1, no need to pass this parameter if not required."
          }
        ],
        "x-temu-request-parameters": [
          {
            "name": "request",
            "type": "OBJECT",
            "required": false
          },
          {
            "name": "parentAfterSalesSn",
            "type": "STRING",
            "required": true,
            "description": "After-sales Parent Order Number, Required"
          },
          {
            "name": "parentOrderSn",
            "type": "STRING",
            "required": true,
            "description": "Order Number"
          },
          {
            "name": "openApiRefundType",
            "type": "INTEGER",
            "required": true,
            "description": "Refund Type; enumerated as follows:1-Full Refund"
          }
        ],
        "x-temu-response-parameters": [
          {
            "name": "response",
            "type": "OBJECT"
          },
          {
            "name": "success",
            "type": "BOOLEAN",
            "description": "Whether it was successful or not"
          },
          {
            "name": "errorCode",
            "type": "INTEGER",
            "description": "Error code"
          },
          {
            "name": "errorMsg",
            "type": "STRING",
            "description": "Error message"
          },
          {
            "name": "result",
            "type": "OBJECT",
            "description": "Specific information"
          }
        ],
        "x-temu-additional-tables": [
          {
            "label": "Error Code",
            "rows": [
              {
                "Error Code": "130010004",
                "Error Message": "no afterSales found",
                "Error SOP": ""
              },
              {
                "Error Code": "130010005",
                "Error Message": "operate forbid",
                "Error SOP": ""
              },
              {
                "Error Code": "130010003",
                "Error Message": "There were some payable in your account, please process them in the merchant workbench before proceeding.",
                "Error SOP": ""
              },
              {
                "Error Code": "130010000",
                "Error Message": "system error",
                "Error SOP": ""
              },
              {
                "Error Code": "130010001",
                "Error Message": "The parameter is illegal. Please check if the input parameter meets the regulations.",
                "Error SOP": ""
              }
            ]
          },
          {
            "label": "Permission Package",
            "rows": [
              {
                "Permission Package": "Semi Aftersales Management",
                "App type": "private,public"
              },
              {
                "Permission Package": "Local Aftersales Management",
                "App type": "private,public"
              }
            ]
          },
          {
            "label": "To help sellers get more traffic, attract customers, and increase sales, four activities have been launched: Clearance deals, Lightning deals, Official big sale, and Advanced big sale.",
            "rows": [
              {
                "Activity type": "Description",
                "Clearance deals (CD)": "14-day promotion that aims to establish low prices for customers, quickly clear out slow-moving stock, and enhance turnover",
                "Lightning deals (LD)": "7-day promotion with significantly discounted items",
                "Official big sale(OBG)": "Low-barrier entry for time-limited discounts",
                "Advanced big sale(ABG)": "series of promotional events to feature products that match the festive spirit or seasonal occasions"
              },
              {
                "Activity type": "Key points",
                "Clearance deals (CD)": "Exclusive homepage bannerClearance sale or reductions on discontinued sizes",
                "Lightning deals (LD)": "Featured deals section on the homepageEncourages quick purchases and increases sales",
                "Official big sale(OBG)": "Increases traffic and recommendationsIntense promotional atmosphere",
                "Advanced big sale(ABG)": "Activity banner on the homepageLeverage peak shopping periods and customer interests"
              },
              {
                "Activity type": "When to use",
                "Clearance deals (CD)": "Works best for overstocked items or significantly discounted items",
                "Lightning deals (LD)": "Works best for in-demand items or significantly discounted items",
                "Official big sale(OBG)": "Most suitable for long-term discounts and products with a low entry barrier",
                "Advanced big sale(ABG)": "Most suitable for products that align with upcoming holiday themes or meet seasonal demand"
              },
              {
                "Activity type": "Duration",
                "Clearance deals (CD)": "14 days",
                "Lightning deals (LD)": "7 days",
                "Official big sale(OBG)": "Variable time",
                "Advanced big sale(ABG)": ""
              },
              {
                "Activity type": "Minimum discount requirements",
                "Clearance deals (CD)": "Refer to the product discount requirements provided on the reference system.",
                "Lightning deals (LD)": "",
                "Official big sale(OBG)": "",
                "Advanced big sale(ABG)": ""
              },
              {
                "Activity type": "Activity price",
                "Clearance deals (CD)": "In general, the lower the activity base price, the lower the activity price.",
                "Lightning deals (LD)": "",
                "Official big sale(OBG)": "",
                "Advanced big sale(ABG)": ""
              }
            ]
          },
          {
            "label": "### **Recommended products:**",
            "rows": [
              {
                "**Product name**": "**Variations**",
                "Displays the product picture + name + ID": "Displays variations + SKU ID + SKU"
              },
              {
                "**Product name**": "**Daily （base） price**",
                "Displays the product picture + name + ID": "Displays the corresponding SKU price"
              },
              {
                "**Product name**": "**Activity （base） price**",
                "Displays the product picture + name + ID": "The base price you set for activities, which can be sold at the activity price during the activity period"
              },
              {
                "**Product name**": "**Activity quantity**",
                "Displays the product picture + name + ID": "The quantity you set for participating activities. It will be deducted from the available quantity until the activity ends or you leave the activity"
              }
            ]
          }
        ],
        "x-temu-examples": [
          {
            "language": "text",
            "content": "curl -X POST \\\n'https://openapi-b-global.temu.com/openapi/router' \\\n -H 'content-type: application/json' \\\n -d '{\n  \"access_token\" : \"test\",\n  \"parentAfterSalesSn\" : \"test\",\n  \"app_key\" : \"test\",\n  \"parentOrderSn\" : \"test\",\n  \"openApiRefundType\" : 1,\n  \"sign\" : \"test\",\n  \"data_type\" : \"test\",\n  \"type\" : \"test\",\n  \"version\" : \"test\",\n  \"timestamp\" : \"test\"\n}'",
            "truncated": false
          },
          {
            "language": "text",
            "content": "{\n  \"errorCode\": 1,\n  \"success\": true,\n  \"errorMsg\": \"test\"\n}",
            "truncated": false
          }
        ],
        "x-temu-source": {
          "document": "Temu全球API文档.md",
          "path": "C:\\Users\\Administrator\\Downloads\\Temu全球API文档.md",
          "startLine": 15708,
          "endLine": 15923,
          "contentSha256": "c0cd605a95610fb9680ea9fa804e46e8bb0ed31ceeb94b2ed1a9acf8952d3501"
        }
      }
    }
  },
  "definitions": {
    "temu_aftersales_refund_issueRequest": {
      "type": "object",
      "additionalProperties": true,
      "properties": {
        "type": {
          "type": "string",
          "x-temu-type": "STRING",
          "description": "API name,eg:bg.* Must be `temu.aftersales.refund.issue` for this operation.",
          "enum": [
            "temu.aftersales.refund.issue"
          ],
          "default": "temu.aftersales.refund.issue"
        },
        "app_key": {
          "type": "string",
          "x-temu-type": "STRING"
        },
        "access_token": {
          "type": "string",
          "x-temu-type": "STRING",
          "description": "A secure token for access control."
        },
        "sign": {
          "type": "string",
          "x-temu-type": "STRING"
        },
        "timestamp": {
          "type": "string",
          "x-temu-type": "STRING",
          "description": "The timestamp is in UNIX time format (seconds), with a length of 10 digits, and should be within a range of 300 seconds before the current time to 300 seconds after the current time."
        },
        "data_type": {
          "type": "string",
          "x-temu-type": "STRING",
          "description": "The data format of the request response is fixed as JSON for optional parameters."
        },
        "version": {
          "type": "string",
          "x-temu-type": "STRING",
          "description": "API version, defaults to V1, no need to pass this parameter if not required."
        },
        "request": {
          "type": "object",
          "additionalProperties": true,
          "x-temu-type": "OBJECT"
        },
        "parentAfterSalesSn": {
          "type": "string",
          "x-temu-type": "STRING",
          "description": "After-sales Parent Order Number, Required"
        },
        "parentOrderSn": {
          "type": "string",
          "x-temu-type": "STRING",
          "description": "Order Number"
        },
        "openApiRefundType": {
          "type": "integer",
          "format": "int32",
          "x-temu-type": "INTEGER",
          "description": "Refund Type; enumerated as follows:1-Full Refund"
        }
      },
      "required": [
        "type",
        "app_key",
        "access_token",
        "sign",
        "timestamp",
        "parentAfterSalesSn",
        "parentOrderSn",
        "openApiRefundType"
      ]
    },
    "temu_aftersales_refund_issueResponse": {
      "type": "object",
      "additionalProperties": true,
      "properties": {
        "response": {
          "type": "object",
          "additionalProperties": true,
          "x-temu-type": "OBJECT"
        },
        "success": {
          "type": "boolean",
          "x-temu-type": "BOOLEAN",
          "description": "Whether it was successful or not"
        },
        "errorCode": {
          "type": "integer",
          "format": "int32",
          "x-temu-type": "INTEGER",
          "description": "Error code"
        },
        "errorMsg": {
          "type": "string",
          "x-temu-type": "STRING",
          "description": "Error message"
        },
        "result": {
          "type": "object",
          "additionalProperties": true,
          "x-temu-type": "OBJECT",
          "description": "Specific information"
        }
      }
    }
  },
  "x-temu-source": {
    "document": "Temu全球API文档.md",
    "path": "C:\\Users\\Administrator\\Downloads\\Temu全球API文档.md",
    "startLine": 15708,
    "endLine": 15923,
    "contentSha256": "c0cd605a95610fb9680ea9fa804e46e8bb0ed31ceeb94b2ed1a9acf8952d3501"
  },
  "x-temu-api-type": "temu.aftersales.refund.issue",
  "x-temu-region-module": "temu-global-api"
}
